LICENCE.txt
MANIFEST.in
README.rst
setup.py
sveedocuments/HELP.rst
sveedocuments/__init__.py
sveedocuments/admin.py
sveedocuments/assets.py
sveedocuments/crumbs.py
sveedocuments/models.py
sveedocuments/parser.py
sveedocuments/settings.py
sveedocuments/urls.py
sveedocuments/urls_board.py
sveedocuments.egg-info/PKG-INFO
sveedocuments.egg-info/SOURCES.txt
sveedocuments.egg-info/dependency_links.txt
sveedocuments.egg-info/not-zip-safe
sveedocuments.egg-info/requires.txt
sveedocuments.egg-info/top_level.txt
sveedocuments/forms/__init__.py
sveedocuments/forms/attachment.py
sveedocuments/forms/crispies.py
sveedocuments/forms/insert.py
sveedocuments/forms/page.py
sveedocuments/locale/es/LC_MESSAGES/django.mo
sveedocuments/locale/es/LC_MESSAGES/django.po
sveedocuments/locale/fr/LC_MESSAGES/django.mo
sveedocuments/locale/fr/LC_MESSAGES/django.po
sveedocuments/management/__init__.py
sveedocuments/management/commands/__init__.py
sveedocuments/management/commands/documents.py
sveedocuments/management/commands/documents_export.py
sveedocuments/management/commands/extractor.py
sveedocuments/migrations/0001_initial.py
sveedocuments/migrations/__init__.py
sveedocuments/static/css/sveedocuments_app.css
sveedocuments/static/fonts/sveedocuments.eot
sveedocuments/static/fonts/sveedocuments.svg
sveedocuments/static/fonts/sveedocuments.ttf
sveedocuments/static/fonts/sveedocuments.woff
sveedocuments/static/images/list-tree/list-tree-alt-lastnode.png
sveedocuments/static/images/list-tree/list-tree-alt-node.png
sveedocuments/static/images/list-tree/list-tree-alt-vline.png
sveedocuments/static/images/list-tree/list-tree-bold-lastnode.png
sveedocuments/static/images/list-tree/list-tree-bold-node.png
sveedocuments/static/images/list-tree/list-tree-bold-vline.png
sveedocuments/static/images/list-tree/list-tree-lastnode.png
sveedocuments/static/images/list-tree/list-tree-node.png
sveedocuments/static/images/list-tree/list-tree-vline.png
sveedocuments/static/images/list-tree/ul-end.gif
sveedocuments/static/images/list-tree/ul-long.gif
sveedocuments/static/images/notices/about.png
sveedocuments/static/images/notices/alert.png
sveedocuments/static/images/notices/announce.png
