Metadata-Version: 1.1
Name: sveedocuments
Version: 1.1.1
Summary: 
